topsis/102203234.py
topsis/__init__.py
topsis/__main__.py
Topsis_Guramrit_102203234-1.0.3.dist-info/LICENSE
Topsis_Guramrit_102203234-1.0.3.dist-info/METADATA
Topsis_Guramrit_102203234-1.0.3.dist-info/WHEEL
Topsis_Guramrit_102203234-1.0.3.dist-info/entry_points.txt
Topsis_Guramrit_102203234-1.0.3.dist-info/top_level.txt
Topsis_Guramrit_102203234-1.0.3.dist-info/RECORD
